mythic_payloadtype_container/MythicCommandBase.py
mythic_payloadtype_container/MythicRPC.py
mythic_payloadtype_container/PayloadBuilder.py
mythic_payloadtype_container/__init__.py
mythic_payloadtype_container/config.py
mythic_payloadtype_container/mythic_service.py
mythic_payloadtype_container-0.1.18.dist-info/METADATA
mythic_payloadtype_container-0.1.18.dist-info/WHEEL
mythic_payloadtype_container-0.1.18.dist-info/top_level.txt
mythic_payloadtype_container-0.1.18.dist-info/RECORD
