Metadata-Version: 2.1
Name: mythic-payloadtype-container
Version: 0.1.18
Summary: Functionality for Mythic Payload Type Containers
Home-page: https://docs.mythic-c2.net/customizing/payload-type-development
Author: @its_a_feature_
Author-email: 
License: BSD3
Platform: UNKNOWN
Classifier: License :: Other/Proprietary License
Classifier: Programming Language :: Python :: 3
Classifier: Programming Language :: Python :: 3.8
Requires-Dist: aio-pika (==6.8.0)
Requires-Dist: dynaconf
